libdata/__init__.py
libdata/common.py
libdata/config.py
libdata/fs.py
libdata/json.py
libdata/json_dir.py
libdata/jsonl.py
libdata/milvus.py
libdata/mongodb.py
libdata/mysql.py
libdata/redis.py
libdata/url.py
libdata/yaml_dir.py
libdata-1.4.2.dist-info/LICENSE
libdata-1.4.2.dist-info/METADATA
libdata-1.4.2.dist-info/WHEEL
libdata-1.4.2.dist-info/top_level.txt
libdata-1.4.2.dist-info/zip-safe
libdata-1.4.2.dist-info/RECORD
