Metadata-Version: 2.2
Name: libdata
Version: 1.4.2
Summary: Unified interface to access data.
Home-page: https://github.com/XoriieInpottn/libdata
Author: xi
Author-email: gylv@mail.ustc.edu.cn
License: MIT
Platform: any
Classifier: Programming Language :: Python :: 3
License-File: LICENSE
Requires-Dist: pydantic
Requires-Dist: tqdm
Requires-Dist: PyYAML
Requires-Dist: numpy
Requires-Dist: scipy
Requires-Dist: pymongo
Requires-Dist: pymilvus
Requires-Dist: redis
Requires-Dist: mysql-connector-python
Requires-Dist: fsspec
Requires-Dist: s3fs
Dynamic: author
Dynamic: author-email
Dynamic: classifier
Dynamic: description
Dynamic: description-content-type
Dynamic: home-page
Dynamic: license
Dynamic: platform
Dynamic: requires-dist
Dynamic: summary
